decklist/__init__.py
decklist/deck.py
decklist/parse.py
decklist/setcodes.py
decklist-0.2.0.dist-info/LICENSE
decklist-0.2.0.dist-info/METADATA
decklist-0.2.0.dist-info/WHEEL
decklist-0.2.0.dist-info/top_level.txt
decklist-0.2.0.dist-info/RECORD
